interpretability_engine/__init__.py
interpretability_engine/interpretability_engine.py
interpretability_engine/model.py
interpretability_engine/routes.py
interpretability_engine/utils.py
interpretability_engine/methods/__init__.py
interpretability_engine/methods/base.py
interpretability_engine/methods/pdp.py
interpretability_engine-0.11.2.data/scripts/interpretability-engine
interpretability_engine-0.11.2.dist-info/AUTHORS
interpretability_engine-0.11.2.dist-info/LICENSE
interpretability_engine-0.11.2.dist-info/METADATA
interpretability_engine-0.11.2.dist-info/WHEEL
interpretability_engine-0.11.2.dist-info/top_level.txt
interpretability_engine-0.11.2.dist-info/RECORD
